mqflow/__init__.py
mqflow/broker/__init__.py
mqflow/broker/base.py
mqflow/config.py
mqflow/console.py
mqflow/consumer/__init__.py
mqflow/consumer/base.py
mqflow/exceptions/__init__.py
mqflow/exceptions/broker.py
mqflow/pipeline/__init__.py
mqflow/pipeline/base.py
mqflow/pipeline/sequential.py
mqflow/producer/__init__.py
mqflow/producer/base.py
mqflow/utils/__init__.py
mqflow/version.py
mqflow-0.4.0.dist-info/LICENSE
mqflow-0.4.0.dist-info/WHEEL
mqflow-0.4.0.dist-info/METADATA
mqflow-0.4.0.dist-info/RECORD
